CellAutDisp/__init__.py
CellAutDisp/analytics.py
CellAutDisp/calibration.py
CellAutDisp/cellautom_dispersion.py
CellAutDisp/create_weighted_matrix.py
CellAutDisp/data_preparation.py
CellAutDisp/meteorepeats.py
CellAutDisp/performance_metrics.py
CellAutDisp/provide_adjuster.py
CellAutDisp-0.2.dist-info/LICENSE
CellAutDisp-0.2.dist-info/METADATA
CellAutDisp-0.2.dist-info/WHEEL
CellAutDisp-0.2.dist-info/entry_points.txt
CellAutDisp-0.2.dist-info/top_level.txt
CellAutDisp-0.2.dist-info/RECORD
