Metadata-Version: 2.1
Name: CellAutDisp
Version: 0.2
Requires-Python: >=3.9
License-File: LICENSE
Requires-Dist: numpy (>=1.23.5)
Requires-Dist: pandas
Requires-Dist: matplotlib
Requires-Dist: seaborn
Requires-Dist: joblib
Requires-Dist: geneticalgorithm2
Requires-Dist: datetime
Requires-Dist: xarray-spatial
Requires-Dist: geopandas
Requires-Dist: shapely
Requires-Dist: scipy
Requires-Dist: xarray
Requires-Dist: scikit-learn
Requires-Dist: pyarrow (>=14.0.1)
Requires-Dist: dask-expr
Requires-Dist: dask (==2023.7.1)
Requires-Dist: urllib3 (==1.26.16)
Requires-Dist: matplotlib-scalebar
Requires-Dist: func-timeout
Requires-Dist: rioxarray
